CHANGES.txt
LICENSE.txt
MANIFEST.in
README.txt
setup.py
js/__init__.py
js.angular_ui_calendar.egg-info/PKG-INFO
js.angular_ui_calendar.egg-info/SOURCES.txt
js.angular_ui_calendar.egg-info/dependency_links.txt
js.angular_ui_calendar.egg-info/entry_points.txt
js.angular_ui_calendar.egg-info/namespace_packages.txt
js.angular_ui_calendar.egg-info/not-zip-safe
js.angular_ui_calendar.egg-info/requires.txt
js.angular_ui_calendar.egg-info/top_level.txt
js/angular_ui_calendar/__init__.py
js/angular_ui_calendar/test_angular-ui_ui-calendar.txt
js/angular_ui_calendar/resources/calendar.js