Metadata-Version: 1.0
Name: js.angular-ui-calendar
Version: 0.9.0-beta.1
Summary: Fanstatic packaging of angular-ui ui-calendar
Home-page: UNKNOWN
Author: Fanstatic Developers
Author-email: fanstatic@googlegroups.com
License: BSD
Platform: UNKNOWN
